Workbook

Sheet Reglas
B1: Árbol de tecnologías v0.2 — 203 propuestas en 12 ramas con columna vertebral
B2: Todo es una propuesta para corregir. Las 36 tecnologías marcadas como 'Tuya' conservan tus efectos; los nombres, prerrequisitos y el resto son míos.
B4: Parámetros (celdas amarillas: se pueden cambiar)
B5: Costo por nivel (puntos de tecnología) | C5: 20 | D5: Tuyo: nivel 1 = 20, nivel 2 = 40 … nivel 5 = 100. El costo de cada tecnología es Nivel × este valor.
B6: Mín. de tecnologías de nivel 1 para investigar una de nivel 2 | C6: 3 | D6: Propuesta mía. Cuentan tecnologías de cualquier rama, vertebrales u opcionales.
B7: Mín. de tecnologías de nivel 2 para investigar una de nivel 3 | C7: 5 | D7: Propuesta mía.
B8: Mín. de tecnologías de nivel 3 para investigar una de nivel 4 | C8: 6 | D8: Propuesta mía.
B9: Mín. de tecnologías de nivel 4 para investigar una de nivel 5 | C9: 6 | D9: Propuesta mía.
B11: Cómo funciona el árbol
B12: Hay 12 ramas. Cada rama tiene una COLUMNA VERTEBRAL (de 6 a 7 tecnologías, con al menos una por nivel y una sola de nivel 5) y tecnologías OPCIONALES (especializaciones y extras).
B13: Para investigar cualquier tecnología de nivel 5 de una rama hay que haber completado antes la columna vertebral de esa rama hasta el nivel 4. Las opcionales no cuentan para completar la columna.
B14: Además, para investigar una tecnología de nivel n hace falta el mínimo de tecnologías del nivel n−1 indicado arriba (de cualquier rama), y todos sus prerrequisitos directos (máximo 2, de nivel menor).
B15: Un edificio se desbloquea con su tecnología de nivel 1. Las de niveles 2 a 5 lo mejoran o lo especializan ('Esp.'). Las tecnologías de zona desbloquean los niveles 2 y 3 de las zonas especializadas (nivel 2 con tecnología de nivel 2; nivel 3 con la de nivel 4).
B16: Tipo = Civil, Construcción o Militar. Cuartel, Fortificación y las máquinas de asedio se marcan como Militar; los demás edificios, como Construcción.
B18: Victoria tecnológica (5 tecnologías de nivel 5)
B19: Con 5 tecnologías de nivel 5 de RAMAS DISTINTAS: camino más barato | C19: 1700 | D19: Calculado por script con los mínimos 3 / 5 / 6 / 6 y con los 9 edificios básicos ya desarrollados (36 tecnologías contando esas 9). Entre las combinaciones de 5 ramas, el costo va de 1700 a 2040.
B20: Si bastara con CUALQUIER 5 de nivel 5 (aunque sean de la misma rama) | C20: 1500 | D20: Estimación: se lograría con solo 2 ramas (Logística y Armas y unidades), por eso recomiendo exigir ramas distintas.
B21: Costo de completar una sola columna vertebral (promedio) | C21: 363 | D21: Entre 280 y 440 según la rama, descontando las tecnologías iniciales (ver hoja 'Ramas').
B23: Columnas de la hoja 'Tecnologías'
B24: Columna | C24: Vertebral = obligatoria para completar la rama y poder llegar al nivel 5. Opcional = especialización o extra que no cuenta para completarla.
B25: Valoración (1–5) | C25: 5 = muy buena (clara, divertida y bien balanceada); 4 = buena; 3 = aceptable o situacional; 2 = débil, redundante o arriesgada; 1 = problemática. Es mi opinión, para discutir.
B26: Riesgo de balance | C26: Bajo / Medio / Alto: qué tan probable es que desbalancee el juego. Se mide con el simulador, no a ojo.
B27: Origen | C27: 'Tuya' = viene de tu lista (36 tecnologías, con tus efectos). 'Mía' = propuesta nueva.
B28: Subrama | C28: La agrupación temática anterior (30 grupos), útil para filtrar por tema. La Rama (12) es la que cuenta para el árbol.
B29: Esp. | C29: Especialización de un edificio: variante que eliges para ese edificio, distinta de la mejora general.
B31: Cambios respecto a la versión anterior
B32: • Los 9 edificios básicos (Almacenes, Caminos, Hospitales, Cuarteles, Fortificaciones, Bibliotecas, Molinos, Talleres y Mercados) vienen ya desarrollados al inicio (columna Inicial = Sí, costo 0). Cuentan para los mínimos del nivel 1.
B33: • La investigación ya no es instantánea: cada tecnología avanza cada paso hasta la capacidad de los científicos asignados a investigar (2 de ciencia por científico, más el bono de la zona de tecnología). Un científico genera 2 de ciencia o usa 2 para investigar, no ambas cosas.
B34: • Se eliminó 'Pacificación' (contradecía el sistema de capturas) y se reemplazaron 'Asedio' y 'Catapultas' por 6 tecnologías de máquinas de asedio (arietes y lanzapiedras, con 3 niveles cada una).
B35: • 'Gremio mercantil' pasó a llamarse 'Gran compañía' para no confundirse con 'Gremios mercantiles' (zona comercial nivel 3).
B36: • Varios prerrequisitos de las tecnologías vertebrales se cambiaron para que cada columna dependa solo de sí misma.
B38: Supuestos y dudas abiertas
B39: • Los bonos de 'Esp.' de Almacén por nivel (+10, +20, +30, +100) se asumen NO acumulables: cada uno reemplaza al anterior.
B40: • Se asume que un mismo edificio tiene una sola especialización a la vez.
B41: • 'Camino militar I' dice +1 de iniciativa. Como el número menor actúa primero, ¿es más lento o más rápido? Se propone −1 (más rápido).
B42: • Hospital imperial (+2 de vida a todos) es una tecnología tuya y es el nivel 5 de la columna de Sanidad: obliga a quien quiera esa rama a tomarla. Está marcada con riesgo alto.
B43: • Varias tecnologías usan mecánicas aún no definidas: zonas riesgosas, vender recursos (Exportaciones), mercenarios, rendiciones por intimidación. Decidir si se quieren.
B44: • El mínimo de tecnologías del nivel anterior cuenta tecnologías de cualquier rama. Se puede exigir que sean del mismo tipo.

Sheet Tecnologías
A1: ID | B1: Nombre | C1: Nivel | D1: Costo | E1: Tipo | F1: Rama | G1: Columna | H1: Subrama | I1: Categoría de efecto | J1: Efecto | K1: Prerrequisitos directos | L1: Mín. del nivel anterior | M1: Origen | N1: Valoración (1–5) | O1: Riesgo de balance | P1: Comentario | Q1: Inicial
A2: T001 | B2: Arado | C2: 1 | D2: =IF(Q2="Sí",0,C2*Reglas!$C$5) | E2: Civil | F2: Agricultura | G2: Vertebral | H2: Agricultura | I2: Comida | J2: +1 de comida por agricultor. | K2: — | L2: =IF(C2=1,0,CHOOSE(C2-1,Reglas!$C$6,Reglas!$C$7,Reglas!$C$8,Reglas!$C$9)) | M2: Mía | N2: 5 | O2: Bajo | P2: Mejora clara y barata; sin ella, la agricultura se queda atrás.
A3: T002 | B3: Riego | C3: 2 | D3: =IF(Q3="Sí",0,C3*Reglas!$C$5) | E3: Civil | F3: Agricultura | G3: Vertebral | H3: Zonas | I3: Zona especializada | J3: Desbloquea la zona de agricultura nivel 2 (+8 de comida de zona). | K3: Arado (T001) | L3: =IF(C3=1,0,CHOOSE(C3-1,Reglas!$C$6,Reglas!$C$7,Reglas!$C$8,Reglas!$C$9)) | M3: Mía | N3: 4 | O3: Bajo | P3: Pasar del nivel 1 al 2 vale +4 de comida por 40 de tecnología: rentable pronto.
A4: T003 | B4: Huertos familiares | C4: 2 | D4: =IF(Q4="Sí",0,C4*Reglas!$C$5) | E4: Civil | F4: Agricultura | G4: Vertebral | H4: Agricultura | I4: Comida | J4: +1 de comida por poblador normal. | K4: Arado (T001) | L4: =IF(C4=1,0,CHOOSE(C4-1,Reglas!$C$6,Reglas!$C$7,Reglas!$C$8,Reglas!$C$9)) | M4: Mía | N4: 4 | O4: Bajo | P4: Beneficia a las zonas básicas, que son las más comunes al inicio.
A5: T004 | B5: Abonos | C5: 3 | D5: =IF(Q5="Sí",0,C5*Reglas!$C$5) | E5: Civil | F5: Agricultura | G5: Vertebral | H5: Agricultura | I5: Comida | J5: +1 de comida por agricultor (se suma al Arado). | K5: Arado (T001); Huertos familiares (T003) | L5: =IF(C5=1,0,CHOOSE(C5-1,Reglas!$C$6,Reglas!$C$7,Reglas!$C$8,Reglas!$C$9)) | M5: Mía | N5: 4 | O5: Bajo | P5: Escala bien con zonas agrícolas especializadas.
A6: T005 | B6: Cosecha comunal | C6: 4 | D6: =IF(Q6="Sí",0,C6*Reglas!$C$5) | E6: Civil | F6: Agricultura | G6: Vertebral | H6: Zonas | I6: Zona especializada | J6: Desbloquea la zona de agricultura nivel 3 (+12 de comida de zona). | K6: Riego (T002); Abonos (T004) | L6: =IF(C6=1,0,CHOOSE(C6-1,Reglas!$C$6,Reglas!$C$7,Reglas!$C$8,Reglas!$C$9)) | M6: Mía | N6: 4 | O6: Bajo | P6: Cierra la rama de agricultura con un bono grande.
A7: T006 | B7: Granjas modelo | C7: 5 | D7: =IF(Q7="Sí",0,C7*Reglas!$C$5) | E7: Civil | F7: Agricultura | G7: Vertebral | H7: Agricultura | I7: Comida | J7: Desbloquea La Huerta Infinita, la maravilla de Agricultura (única en la partida): +1 de comida por agricultor mientras controles su zona. Solo se puede investigar si nadie la ha construido. | K7: Cosecha comunal (T005) | L7: =IF(C7=1,0,CHOOSE(C7-1,Reglas!$C$6,Reglas!$C$7,Reglas!$C$8,Reglas!$C$9)) | M7: Mía | N7: 3 | O7: Bajo | P7: Por sí sola no da su efecto: lo da la maravilla. Si otro la termina antes, pierdes la obra y recuperas la mitad de la producción, pero conservas la tecnología (cuenta para la victoria tecnológica).
A8: T007 | B8: Molinos | C8: 1 | D8: =IF(Q8="Sí",0,C8*Reglas!$C$5) | E8: Construcción | F8: Agricultura | G8: Opcional | H8: Molino | I8: Desbloqueo de edificio | J8: Permite construir el Molino: +1 de comida por trabajador. | K8: — | L8: =IF(C8=1,0,CHOOSE(C8-1,Reglas!$C$6,Reglas!$C$7,Reglas!$C$8,Reglas!$C$9)) | M8: Tuya | N8: 5 | O8: Bajo | P8: Mejora directa de la comida. Barata de entender y rentable pronto. | Q8: Sí
A9: T008 | B9: Molino de piedra | C9: 2 | D9: =IF(Q9="Sí",0,C9*Reglas!$C$5) | E9: Construcción | F9: Agricultura | G9: Opcional | H9: Molino | I9: Mejora de edificio | J9: El Molino da +2 de comida por trabajador (reemplaza al +1). | K9: Molinos (T007) | L9: =IF(C9=1,0,CHOOSE(C9-1,Reglas!$C$6,Reglas!$C$7,Reglas!$C$8,Reglas!$C$9)) | M9: Mía | N9: 4 | O9: Bajo | P9: Escala bien con el número de trabajadores (Andamios, Grúas).
A10: T009 | B10: Despensas | C10: 2 | D10: =IF(Q10="Sí",0,C10*Reglas!$C$5) | E10: Civil | F10: Agricultura | G10: Opcional | H10: Agricultura | I10: Comida | J10: La muerte por hambre llega a las 3 rondas en vez de 2. | K10: Arado (T001) | L10: =IF(C10=1,0,CHOOSE(C10-1,Reglas!$C$6,Reglas!$C$7,Reglas!$C$8,Reglas!$C$9)) | M10: Mía | N10: 3 | O10: Bajo | P10: Suaviza un castigo duro. Útil para quien se expande rápido y arriesga.
A11: T010 | B11: Pastoreo | C11: 2 | D11: =IF(Q11="Sí",0,C11*Reglas!$C$5) | E11: Civil | F11: Agricultura | G11: Opcional | H11: Terreno y eventos | I11: Terreno | J11: En Praderas, agricultores y pobladores producen +1 de comida adicional. | K11: Arado (T001) | L11: =IF(C11=1,0,CHOOSE(C11-1,Reglas!$C$6,Reglas!$C$7,Reglas!$C$8,Reglas!$C$9)) | M11: Mía | N11: 3 | O11: Medio | P11: Sumada al bono natural de las Praderas, agricultores y pobladores rinden +2 de comida extra. Mismo riesgo: premia al que parte con Praderas.
A12: T011 | B12: Molino-granero | C12: 3 | D12: =IF(Q12="Sí",0,C12*Reglas!$C$5) | E12: Construcción | F12: Agricultura | G12: Opcional | H12: Molino | I12: Especialización de edificio | J12: Esp.: además, el Molino da +1 de comida por cada 10 de comida almacenada en la zona (máximo +3). | K12: Molino de piedra (T008); Almacenes (T073) | L12: =IF(C12=1,0,CHOOSE(C12-1,Reglas!$C$6,Reglas!$C$7,Reglas!$C$8,Reglas!$C$9)) | M12: Mía | N12: 3 | O12: Bajo | P12: Une Molino y Almacén. Solo rinde si ahorras comida, lo que choca con crecer.
A13: T012 | B13: Ganadería | C13: 3 | D13: =IF(Q13="Sí",0,C13*Reglas!$C$5) | E13: Civil | F13: Agricultura | G13: Opcional | H13: Agricultura | I13: Comida | J13: Cada zona de agricultura gana +2 de comida por nivel de zona. | K13: Huertos familiares (T003) | L13: =IF(C13=1,0,CHOOSE(C13-1,Reglas!$C$6,Reglas!$C$7,Reglas!$C$8,Reglas!$C$9)) | M13: Mía | N13: 3 | O13: Medio | P13: Premia la especialización, pero 6 de comida extra en nivel 3 pesa mucho.
A14: T013 | B14: Semillas resistentes | C14: 3 | D14: =IF(Q14="Sí",0,C14*Reglas!$C$5) | E14: Civil | F14: Agricultura | G14: Opcional | H14: Agricultura | I14: Comida | J14: Los eventos negativos que reducen la comida afectan un 50% menos. | K14: Arado (T001) | L14: =IF(C14=1,0,CHOOSE(C14-1,Reglas!$C$6,Reglas!$C$7,Reglas!$C$8,Reglas!$C$9)) | M14: Mía | N14: 3 | O14: Bajo | P14: Buena como seguro, pero depende de qué eventos existan.
A15: T014 | B15: Molino hidráulico | C15: 4 | D15: =IF(Q15="Sí",0,C15*Reglas!$C$5) | E15: Construcción | F15: Agricultura | G15: Opcional | H15: Molino | I15: Mejora de edificio | J15: El Molino da +3 de comida por trabajador (+1 más si la zona es de Ríos). | K15: Molino-granero (T011) | L15: =IF(C15=1,0,CHOOSE(C15-1,Reglas!$C$6,Reglas!$C$7,Reglas!$C$8,Reglas!$C$9)) | M15: Mía | N15: 4 | O15: Medio | P15: Buena sinergia con el terreno. Evita que los Ríos sean solo para arqueros y comercio.
A16: T015 | B16: Irrigación avanzada | C16: 4 | D16: =IF(Q16="Sí",0,C16*Reglas!$C$5) | E16: Civil | F16: Agricultura | G16: Opcional | H16: Agricultura | I16: Comida | J16: +1 de comida por poblador normal (se suma a Huertos familiares). | K16: Abonos (T004) | L16: =IF(C16=1,0,CHOOSE(C16-1,Reglas!$C$6,Reglas!$C$7,Reglas!$C$8,Reglas!$C$9)) | M16: Mía | N16: 4 | O16: Bajo | P16: Bono continuo para zonas básicas.
A17: T016 | B17: Gran molino | C17: 5 | D17: =IF(Q17="Sí",0,C17*Reglas!$C$5) | E17: Construcción | F17: Agricultura | G17: Opcional | H17: Molino | I17: Mejora de edificio | J17: El Molino da +5 de comida por trabajador. | K17: Molino hidráulico (T014) | L17: =IF(C17=1,0,CHOOSE(C17-1,Reglas!$C$6,Reglas!$C$7,Reglas!$C$8,Reglas!$C$9)) | M17: Mía | N17: 3 | O17: Alto | P17: Con 4 trabajadores son +20 de comida por paso, más que una zona de agricultura de nivel 3. Revisar con el simulador.
A18: T017 | B18: Revolución agrícola | C18: 5 | D18: =IF(Q18="Sí",0,C18*Reglas!$C$5) | E18: Civil | F18: Agricultura | G18: Opcional | H18: Agricultura | I18: Comida | J18: Las zonas de agricultura nivel 3 generan +6 de comida adicionales. | K18: Cosecha comunal (T005); Ganadería (T012) | L18: =IF(C18=1,0,CHOOSE(C18-1,Reglas!$C$6,Reglas!$C$7,Reglas!$C$8,Reglas!$C$9)) | M18: Mía | N18: 3 | O18: Medio | P18: Fuerte, pero muy específica: solo sirve con zonas de nivel 3.
A19: T018 | B19: Herramientas | C19: 1 | D19: =IF(Q19="Sí",0,C19*Reglas!$C$5) | E19: Civil | F19: Producción | G19: Vertebral | H19: Producción | I19: Producción | J19: +1 de producción por ingeniero. | K19: — | L19: =IF(C19=1,0,CHOOSE(C19-1,Reglas!$C$6,Reglas!$C$7,Reglas!$C$8,Reglas!$C$9)) | M19: Mía | N19: 5 | O19: Bajo | P19: Mejora clara y barata; base para el plan de edificios.
A20: T019 | B20: Ingeniería básica | C20: 2 | D20: =IF(Q20="Sí",0,C20*Reglas!$C$5) | E20: Civil | F20: Producción | G20: Vertebral | H20: Zonas | I20: Zona especializada | J20: Desbloquea la zona de producción nivel 2 (+8 de producción de zona). | K20: Herramientas (T018) | L20: =IF(C20=1,0,CHOOSE(C20-1,Reglas!$C$6,Reglas!$C$7,Reglas!$C$8,Reglas!$C$9)) | M20: Mía | N20: 4 | O20: Bajo | P20: Buen salto para el plan de edificios.
... A24: T023 | B24: Maquinaria | C24: 5 | D24: =IF(Q24="Sí",0,C24*Reglas!$C$5) | E24: Civil | F24: Producción | G24: Vertebral | H24: Producción | I24: Producción | J24: Desbloquea La Gran Fragua, la maravilla de Producción (única en la partida): +1 de producción por ingeniero mientras controles su zona. Solo se puede investigar si nadie la ha construido. | K24: Ingeniería avanzada (T022) | L24: =IF(C24=1,0,CHOOSE(C24-1,Reglas!$C$6,Reglas!$C$7,Reglas!$C$8,Reglas!$C$9)) | M24: Mía | N24: 3 | O24: Medio | P24: Por sí sola no da su efecto: lo da la maravilla. Si otro la termina antes, pierdes la obra y recuperas la mitad de la producción, pero conservas la tecnología (cuenta para la victoria tecnológica).
A25: T024 | B25: Talleres | C25: 1 | D25: =IF(Q25="Sí",0,C25*Reglas!$C$5) | E25: Construcción | F25: Producción | G25: Opcional | H25: Taller | I25: Desbloqueo de edificio | J25: Permite construir el Taller: +1 de producción por trabajador. | K25: — | L25: =IF(C25=1,0,CHOOSE(C25-1,Reglas!$C$6,Reglas!$C$7,Reglas!$C$8,Reglas!$C$9)) | M25: Tuya | N25: 5 | O25: Bajo | P25: Mejora directa de producción; base para armas y edificios. | Q25: Sí
A26: T025 | B26: Taller de herrería | C26: 2 | D26: =IF(Q26="Sí",0,C26*Reglas!$C$5) | E26: Construcción | F26: Producción | G26: Opcional | H26: Taller | I26: Mejora de edificio | J26: El Taller da +2 de producción por trabajador (reemplaza al +1). | K26: Talleres (T024) | L26: =IF(C26=1,0,CHOOSE(C26-1,Reglas!$C$6,Reglas!$C$7,Reglas!$C$8,Reglas!$C$9)) | M26: Mía | N26: 4 | O26: Bajo | P26: Escala bien con los trabajadores extra.
A27: T026 | B27: Aprendices | C27: 2 | D27: =IF(Q27="Sí",0,C27*Reglas!$C$5) | E27: Civil | F27: Producción | G27: Opcional | H27: Producción | I27: Producción | J27: Especializar civiles cuesta 0 de producción en zonas con Taller. | K27: Herramientas (T018); Talleres (T024) | L27: =IF(C27=1,0,CHOOSE(C27-1,Reglas!$C$6,Reglas!$C$7,Reglas!$C$8,Reglas!$C$9)) | M27: Mía | N27: 3 | O27: Medio | P27: Fomenta tener Taller en cada zona; puede volver trivial el costo de especializar.
A28: T027 | B28: Terrazas | C28: 2 | D28: =IF(Q28="Sí",0,C28*Reglas!$C$5) | E28: Civil | F28: Producción | G28: Opcional | H28: Terreno y eventos | I28: Terreno | J28: En Montañas, ingenieros y pobladores producen +1 de producción adicional. | K28: Herramientas (T018) | L28: =IF(C28=1,0,CHOOSE(C28-1,Reglas!$C$6,Reglas!$C$7,Reglas!$C$8,Reglas!$C$9)) | M28: Mía | N28: 3 | O28: Medio | P28: Sumada al bono natural de las Montañas, un ingeniero rinde +2 de producción extra en esa zona. Premia buscar el terreno, pero también inclina el mapa a favor de quien parte con Montañas.
A29: T028 | B29: Taller de armería | C29: 3 | D29: =IF(Q29="Sí",0,C29*Reglas!$C$5) | E29: Construcción | F29: Producción | G29: Opcional | H29: Taller | I29: Especialización de edificio | J29: Esp.: las armas fabricadas en este Taller cuestan 1 de producción menos. | K29: Taller de herrería (T025); Cuarteles (T158) | L29: =IF(C29=1,0,CHOOSE(C29-1,Reglas!$C$6,Reglas!$C$7,Reglas!$C$8,Reglas!$C$9)) | M29: Mía | N29: 3 | O29: Bajo | P29: Une economía y guerra. Los costos de armas (3 a 6) son bajos, así que el ahorro puede ser pequeño.
A30: T029 | B30: Taller de maquinaria | C30: 4 | D30: =IF(Q30="Sí",0,C30*Reglas!$C$5) | E30: Construcción | F30: Producción | G30: Opcional | H30: Taller | I30: Mejora de edificio | J30: El Taller da +3 de producción por trabajador. | K30: Taller de armería (T028) | L30: =IF(C30=1,0,CHOOSE(C30-1,Reglas!$C$6,Reglas!$C$7,Reglas!$C$8,Reglas!$C$9)) | M30: Mía | N30: 4 | O30: Medio | P30: Es el camino natural hacia las Maravillas.
A31: T030 | B31: Línea de ensamblaje | C31: 4 | D31: =IF(Q31="Sí",0,C31*Reglas!$C$5) | E31: Civil | F31: Producción | G31: Opcional | H31: Producción | I31: Producción | J31: Cada ingeniero que construye puede usar +1 de producción por paso (se suma a Cuadrillas de obra). | K31: Cuadrillas de obra (T092); Minería (T021) | L31: =IF(C31=1,0,CHOOSE(C31-1,Reglas!$C$6,Reglas!$C$7,Reglas!$C$8,Reglas!$C$9)) | M31: Mía | N31: 3 | O31: Medio | P31: Fuerte para los planes de edificios y Maravillas.
A32: T031 | B32: Gran manufactura | C32: 5 | D32: =IF(Q32="Sí",0,C32*Reglas!$C$5) | E32: Construcción | F32: Producción | G32: Opcional | H32: Taller | I32: Mejora de edificio | J32: El Taller da +5 de producción por trabajador. | K32: Taller de maquinaria (T029) | L32: =IF(C32=1,0,CHOOSE(C32-1,Reglas!$C$6,Reglas!$C$7,Reglas!$C$8,Reglas!$C$9)) | M32: Mía | N32: 3 | O32: Alto | P32: Con 4 trabajadores son +20 de producción por paso: una Maravilla cada 25 pasos solo con este edificio. Vigilar.
A33: T032 | B33: Moneda | C33: 1 | D33: =IF(Q33="Sí",0,C33*Reglas!$C$5) | E33: Civil | F33: Comercio | G33: Vertebral | H33: Comercio | I33: Oro | J33: +1 de oro por comerciante. | K33: — | L33: =IF(C33=1,0,CHOOSE(C33-1,Reglas!$C$6,Reglas!$C$7,Reglas!$C$8,Reglas!$C$9)) | M33: Mía | N33: 5 | O33: Bajo | P33: Mejora clara y barata; hace viable la zona comercial.
A34: T033 | B34: Rutas comerciales | C34: 2 | D34: =IF(Q34="Sí",0,C34*Reglas!$C$5) | E34: Civil | F34: Comercio | G34: Vertebral | H34: Zonas | I34: Zona especializada | J34: Desbloquea la zona comercial nivel 2 (+8 de oro de zona). | K34: Moneda (T032) | L34: =IF(C34=1,0,CHOOSE(C34-1,Reglas!$C$6,Reglas!$C$7,Reglas!$C$8,Reglas!$C$9)) | M34: Mía | N34: 4 | O34: Bajo | P34: Pasa de 4 a 8 de oro de zona; muy buena inversión.
A35: T034 | B35: Caravanas | C35: 2 | D35: =IF(Q35="Sí",0,C35*Reglas!$C$5) | E35: Civil | F35: Comercio | G35: Vertebral | H35: Comercio | I35: Oro | J35: Los primeros 5 de comida o producción que muevas cada paso no pagan logística. | K35: Moneda (T032) | L35: =IF(C35=1,0,CHOOSE(C35-1,Reglas!$C$6,Reglas!$C$7,Reglas!$C$8,Reglas!$C$9)) | M35: Mía | N35: 4 | O35: Bajo | P35: Hace sentir menos el costo del oro al inicio.
A36: T035 | B36: Contabilidad | C36: 3 | D36: =IF(Q36="Sí",0,C36*Reglas!$C$5) | E36: Civil | F36: Comercio | G36: Vertebral | H36: Comercio | I36: Oro | J36: Comprar un recurso faltante cuesta 2 de oro (en vez de 3). | K36: Moneda (T032); Caravanas (T034) | L36: =IF(C36=1,0,CHOOSE(C36-1,Reglas!$C$6,Reglas!$C$7,Reglas!$C$8,Reglas!$C$9)) | M36: Mía | N36: 4 | O36: Bajo | P36: Reduce el castigo de las escaseces.
A37: T036 | B37: Gremios mercantiles | C37: 4 | D37: =IF(Q37="Sí",0,C37*Reglas!$C$5) | E37: Civil | F37: Comercio | G37: Vertebral | H37: Zonas | I37: Zona especializada | J37: Desbloquea la zona comercial nivel 3 (+12 de oro de zona). | K37: Rutas comerciales (T033); Contabilidad (T035) | L37: =IF(C37=1,0,CHOOSE(C37-1,Reglas!$C$6,Reglas!$C$7,Reglas!$C$8,Reglas!$C$9)) | M37: Mía | N37: 4 | O37: Bajo | P37: Empuja hacia los 1000 de oro.
A38: T037 | B38: Gran compañía | C38: 5 | D38: =IF(Q38="Sí",0,C38*Reglas!$C$5) | E38: Civil | F38: Comercio | G38: Vertebral | H38: Comercio | I38: Oro | J38: Desbloquea La Lonja Dorada, la maravilla de Comercio (única en la partida): +1 de oro por comerciante mientras controles su zona. Solo se puede investigar si nadie la ha construido. | K38: Gremios mercantiles (T036) | L38: =IF(C38=1,0,CHOOSE(C38-1,Reglas!$C$6,Reglas!$C$7,Reglas!$C$8,Reglas!$C$9)) | M38: Mía | N38: 3 | O38: Bajo | P38: Por sí sola no da su efecto: lo da la maravilla. Si otro la termina antes, pierdes la obra y recuperas la mitad de la producción, pero conservas la tecnología (cuenta para la victoria tecnológica).
A39: T038 | B39: Mercados | C39: 1 | D39: =IF(Q39="Sí",0,C39*Reglas!$C$5) | E39: Construcción | F39: Comercio | G39: Opcional | H39: Mercado | I39: Desbloqueo de edificio | J39: Permite construir el Mercado: +1 de oro por trabajador. | K39: — | L39: =IF(C39=1,0,CHOOSE(C39-1,Reglas!$C$6,Reglas!$C$7,Reglas!$C$8,Reglas!$C$9)) | M39: Tuya | N39: 5 | O39: Bajo | P39: Primer ingreso de oro fuera de la zona comercial. | Q39: Sí
A40: T039 | B40: Mercado central | C40: 2 | D40: =IF(Q40="Sí",0,C40*Reglas!$C$5) | E40: Construcción | F40: Comercio | G40: Opcional | H40: Mercado | I40: Mejora de edificio | J40: El Mercado da +2 de oro por trabajador (reemplaza al +1). | K40: Mercados (T038) | L40: =IF(C40=1,0,CHOOSE(C40-1,Reglas!$C$6,Reglas!$C$7,Reglas!$C$8,Reglas!$C$9)) | M40: Mía | N40: 4 | O40: Bajo | P40: Escala bien con los trabajadores extra.
A41: T040 | B41: Impuestos | C41: 2 | D41: =IF(Q41="Sí",0,C41*Reglas!$C$5) | E41: Civil | F41: Comercio | G41: Opcional | H41: Comercio | I41: Oro | J41: +1 de oro por cada 2 zonas que controles. | K41: Moneda (T032) | L41: =IF(C41=1,0,CHOOSE(C41-1,Reglas!$C$6,Reglas!$C$7,Reglas!$C$8,Reglas!$C$9)) | M41: Mía | N41: 3 | O41: Medio | P41: Premia expandirse. Con 12 zonas serían +6 de oro: moderado.
A42: T041 | B42: Exportaciones | C42: 2 | D42: =IF(Q42="Sí",0,C42*Reglas!$C$5) | E42: Civil | F42: Comercio | G42: Opcional | H42: Comercio | I42: Oro | J42: Puedes vender 2 de comida o producción de tu almacén por 1 de oro (por orden). | K42: Moneda (T032) | L42: =IF(C42=1,0,CHOOSE(C42-1,Reglas!$C$6,Reglas!$C$7,Reglas!$C$8,Reglas!$C$9)) | M42: Mía | N42: 3 | O42: Medio | P42: Introduce la venta de recursos, que hoy no existe. Decidir si se quiere.
A43: T042 | B43: Comercio fluvial | C43: 2 | D43: =IF(Q43="Sí",0,C43*Reglas!$C$5) | E43: Civil | F43: Comercio | G43: Opcional | H43: Terreno y eventos | I43: Terreno | J43: En Ríos, los comerciantes generan +1 de oro adicional. | K43: Moneda (T032) | L43: =IF(C43=1,0,CHOOSE(C43-1,Reglas!$C$6,Reglas!$C$7,Reglas!$C$8,Reglas!$C$9)) | M43: Mía | N43: 3 | O43: Medio | P43: Hace de los Ríos el mejor lugar para comerciar (+2 de oro por comerciante). Combina con el bono de arqueros defensores del mismo terreno.
A44: T043 | B44: Comercio maderero | C44: 2 | D44: =IF(Q44="Sí",0,C44*Reglas!$C$5) | E44: Civil | F44: Comercio | G44: Opcional | H44: Terreno y eventos | I44: Terreno | J44: En Bosques, los comerciantes generan +1 de oro adicional. | K44: Moneda (T032) | L44: =IF(C44=1,0,CHOOSE(C44-1,Reglas!$C$6,Reglas!$C$7,Reglas!$C$8,Reglas!$C$9)) | M44: Mía | N44: 3 | O44: Medio | P44: Hace de los Bosques el mejor lugar para comerciar (+2 de oro por comerciante). Los Bosques ya favorecen a arqueros atacantes.
A45: T044 | B45: Mercado de trueque | C45: 3 | D45: =IF(Q45="Sí",0,C45*Reglas!$C$5) | E45: Construcción | F45: Comercio | G45: Opcional | H45: Mercado | I45: Especialización de edificio | J45: Esp.: comprar un recurso faltante en esta zona cuesta 1 de oro menos. | K45: Mercado central (T039) | L45: =IF(C45=1,0,CHOOSE(C45-1,Reglas!$C$6,Reglas!$C$7,Reglas!$C$8,Reglas!$C$9)) | M45: Mía | N45: 3 | O45: Bajo | P45: Útil cuando hay escasez, pero se solapa con Contabilidad. Pensar en combinarlas con un mínimo de 1.
A46: T045 | B46: Embajadas comerciales | C46: 3 | D46: =IF(Q46="Sí",0,C46*Reglas!$C$5) | E46: Civil | F46: Comercio | G46: Opcional | H46: Comercio | I46: Oro | J46: Mientras tengas paz con otro jugador en una zona fronteriza, ambos ganan +1 de oro por paso. | K46: Caravanas (T034); Embajadores (T123) | L46: =IF(C46=1,0,CHOOSE(C46-1,Reglas!$C$6,Reglas!$C$7,Reglas!$C$8,Reglas!$C$9)) | M46: Mía | N46: 3 | O46: Medio | P46: Premia la paz. Puede dar demasiado oro al vecino al que quieres atacar.
A47: T046 | B47: Banco | C47: 4 | D47: =IF(Q47="Sí",0,C47*Reglas!$C$5) | E47: Construcción | F47: Comercio | G47: Opcional | H47: Mercado | I47: Mejora de edificio | J47: El Mercado da +3 de oro por trabajador. | K47: Mercado de trueque (T044) | L47: =IF(C47=1,0,CHOOSE(C47-1,Reglas!$C$6,Reglas!$C$7,Reglas!$C$8,Reglas!$C$9)) | M47: Mía | N47: 4 | O47: Medio | P47: Empuja hacia los 1000 de oro de la victoria Comercial.
A48: T047 | B48: Casa de moneda | C48: 4 | D48: =IF(Q48="Sí",0,C48*Reglas!$C$5) | E48: Civil | F48: Comercio | G48: Opcional | H48: Comercio | I48: Oro | J48: +1 de oro por comerciante (se suma a Moneda). | K48: Contabilidad (T035) | L48: =IF(C48=1,0,CHOOSE(C48-1,Reglas!$C$6,Reglas!$C$7,Reglas!$C$8,Reglas!$C$9)) | M48: Mía | N48: 4 | O48: Bajo | P48: Bono continuo para la zona comercial.
A49: T048 | B49: Monopolio | C49: 4 | D49: =IF(Q49="Sí",0,C49*Reglas!$C$5) | E49: Civil | F49: Comercio | G49: Opcional | H49: Comercio | I49: Oro | J49: Cada recurso estratégico que controles da +2 de oro por paso. | K49: Impuestos (T040); Contabilidad (T035) | L49: =IF(C49=1,0,CHOOSE(C49-1,Reglas!$C$6,Reglas!$C$7,Reglas!$C$8,Reglas!$C$9)) | M49: Mía | N49: 3 | O49: Bajo | P49: Hace valiosos los recursos estratégicos; depende de cuántos haya en el mapa.
A50: T049 | B50: Seguro mercantil | C50: 4 | D50: =IF(Q50="Sí",0,C50*Reglas!$C$5) | E50: Civil | F50: Comercio | G50: Opcional | H50: Comercio | I50: Oro | J50: Al final de cada paso recuperas un 25% del oro gastado en logística. | K50: Contabilidad (T035) | L50: =IF(C50=1,0,CHOOSE(C50-1,Reglas!$C$6,Reglas!$C$7,Reglas!$C$8,Reglas!$C$9)) | M50: Mía | N50: 2 | O50: Bajo | P50: Añade un cálculo extra de oro por paso al motor y al jugador, a cambio de una ganancia pequeña.
A51: T050 | B51: Bolsa imperial | C51: 5 | D51: =IF(Q51="Sí",0,C51*Reglas!$C$5) | E51: Construcción | F51: Comercio | G51: Opcional | H51: Mercado | I51: Mejora de edificio | J51: El Mercado da +5 de oro por trabajador. | K51: Banco (T046) | L51: =IF(C51=1,0,CHOOSE(C51-1,Reglas!$C$6,Reglas!$C$7,Reglas!$C$8,Reglas!$C$9)) | M51: Mía | N51: 3 | O51: Alto | P51: Con 4 trabajadores son +20 de oro por paso. Con un solo edificio, 1000 de oro serían unos 50 pasos. Vigilar.
... A59: T058 | B59: Enciclopedia | C59: 5 | D59: =IF(Q59="Sí",0,C59*Reglas!$C$5) | E59: Civil | F59: Saber | G59: Vertebral | H59: Saber | I59: Meta (reglas de tecnología) | J59: Desbloquea La Torre de los Sabios, la maravilla de Saber (única en la partida): cada científico genera o usa 3 en vez de 2 mientras controles su zona. Solo se puede investigar si nadie la ha construido. | K59: Método científico (T057); Universidades (T056) | L59: =IF(C59=1,0,CHOOSE(C59-1,Reglas!$C$6,Reglas!$C$7,Reglas!$C$8,Reglas!$C$9)) | M59: Mía | N59: 3 | O59: Medio | P59: Por sí sola no da su efecto: lo da la maravilla. Si otro la termina antes, pierdes la obra y recuperas la mitad de la producción, pero conservas la tecnología (cuenta para la victoria tecnológica).
A60: T059 | B60: Bibliotecas | C60: 1 | D60: =IF(Q60="Sí",0,C60*Reglas!$C$5) | E60: Construcción | F60: Saber | G60: Opcional | H60: Biblioteca | I60: Desbloqueo de edificio | J60: Permite construir la Biblioteca: +1 de tecnología por trabajador. | K60: — | L60: =IF(C60=1,0,CHOOSE(C60-1,Reglas!$C$6,Reglas!$C$7,Reglas!$C$8,Reglas!$C$9)) | M60: Tuya | N60: 5 | O60: Bajo | P60: Hace que la tecnología no dependa solo de los científicos de la capital. | Q60: Sí
A61: T060 | B61: Scriptorium | C61: 2 | D61: =IF(Q61="Sí",0,C61*Reglas!$C$5) | E61: Construcción | F61: Saber | G61: Opcional | H61: Biblioteca | I61: Mejora de edificio | J61: La Biblioteca da +2 de tecnología por trabajador (reemplaza al +1). | K61: Bibliotecas (T059) | L61: =IF(C61=1,0,CHOOSE(C61-1,Reglas!$C$6,Reglas!$C$7,Reglas!$C$8,Reglas!$C$9)) | M61: Mía | N61: 4 | O61: Bajo | P61: Escala bien con los trabajadores extra.
A62: T061 | B62: Calendario | C62: 2 | D62: =IF(Q62="Sí",0,C62*Reglas!$C$5) | E62: Civil | F62: Saber | G62: Opcional | H62: Saber | I62: Eventos | J62: Los eventos se ven con 3 rondas de anticipación (en vez de 2). | K62: Escritura (T052) | L62: =IF(C62=1,0,CHOOSE(C62-1,Reglas!$C$6,Reglas!$C$7,Reglas!$C$8,Reglas!$C$9)) | M62: Mía | N62: 4 | O62: Bajo | P62: Pequeño pero útil para planificar.
A63: T062 | B63: Biblioteca abierta | C63: 3 | D63: =IF(Q63="Sí",0,C63*Reglas!$C$5) | E63: Construcción | F63: Saber | G63: Opcional | H63: Biblioteca | I63: Especialización de edificio | J63: Esp.: las tecnologías que compartes desde esta zona cuestan 1/4 (en vez de la mitad) al vecino, y tú recibes +5 de tecnología por cada una. | K63: Scriptorium (T060) | L63: =IF(C63=1,0,CHOOSE(C63-1,Reglas!$C$6,Reglas!$C$7,Reglas!$C$8,Reglas!$C$9)) | M63: Mía | N63: 3 | O63: Bajo | P63: Fomenta el intercambio. Con vecinos amigos puede acelerar demasiado la victoria tecnológica.
A64: T063 | B64: Espionaje científico | C64: 3 | D64: =IF(Q64="Sí",0,C64*Reglas!$C$5) | E64: Civil | F64: Saber | G64: Opcional | H64: Saber | I64: Información | J64: Ves las tecnologías de todos los jugadores. | K64: Escuelas (T054) | L64: =IF(C64=1,0,CHOOSE(C64-1,Reglas!$C$6,Reglas!$C$7,Reglas!$C$8,Reglas!$C$9)) | M64: Mía | N64: 3 | O64: Bajo | P64: Información sin poder directo; útil para reaccionar a quien va por la victoria tecnológica.
A65: T064 | B65: Atajo del sabio | C65: 3 | D65: =IF(Q65="Sí",0,C65*Reglas!$C$5) | E65: Civil | F65: Saber | G65: Opcional | H65: Saber | I65: Meta (reglas de tecnología) | J65: Una vez por partida, puedes investigar una tecnología sin cumplir el mínimo de tecnologías del nivel anterior. | K65: Escuelas (T054); Calendario (T061) | L65: =IF(C65=1,0,CHOOSE(C65-1,Reglas!$C$6,Reglas!$C$7,Reglas!$C$8,Reglas!$C$9)) | M65: Mía | N65: 3 | O65: Medio | P65: Es un comodín divertido. Cuidado con abrir un camino demasiado corto a las tecnologías de nivel 5.
A66: T065 | B66: Observatorios | C66: 3 | D66: =IF(Q66="Sí",0,C66*Reglas!$C$5) | E66: Civil | F66: Saber | G66: Opcional | H66: Terreno y eventos | I66: Terreno | J66: En Llanuras, los científicos generan +1 de tecnología adicional. | K66: Escritura (T052) | L66: =IF(C66=1,0,CHOOSE(C66-1,Reglas!$C$6,Reglas!$C$7,Reglas!$C$8,Reglas!$C$9)) | M66: Mía | N66: 3 | O66: Alto | P66: Sumada al bono natural de las Llanuras, los científicos generan +2 de tecnología. Es la forma más directa de acelerar el árbol: vigilar.
A67: T066 | B67: Reservas de emergencia | C67: 3 | D67: =IF(Q67="Sí",0,C67*Reglas!$C$5) | E67: Civil | F67: Saber | G67: Opcional | H67: Terreno y eventos | I67: Eventos | J67: Los eventos negativos que aumentan el consumo afectan un 25% menos. | K67: Calendario (T061) | L67: =IF(C67=1,0,CHOOSE(C67-1,Reglas!$C$6,Reglas!$C$7,Reglas!$C$8,Reglas!$C$9)) | M67: Mía | N67: 3 | O67: Bajo | P67: Seguro pequeño; depende de la lista de eventos.
A68: T067 | B68: Archivo | C68: 4 | D68: =IF(Q68="Sí",0,C68*Reglas!$C$5) | E68: Construcción | F68: Saber | G68: Opcional | H68: Biblioteca | I68: Mejora de edificio | J68: La Biblioteca da +3 de tecnología por trabajador. | K68: Biblioteca abierta (T062) | L68: =IF(C68=1,0,CHOOSE(C68-1,Reglas!$C$6,Reglas!$C$7,Reglas!$C$8,Reglas!$C$9)) | M68: Mía | N68: 4 | O68: Medio | P68: Empuja hacia las 5 tecnologías de nivel 5.
A69: T068 | B69: Astronomía | C69: 4 | D69: =IF(Q69="Sí",0,C69*Reglas!$C$5) | E69: Civil | F69: Saber | G69: Opcional | H69: Saber | I69: Eventos | J69: Los eventos se ven con 5 rondas de anticipación. | K69: Calendario (T061) | L69: =IF(C69=1,0,CHOOSE(C69-1,Reglas!$C$6,Reglas!$C$7,Reglas!$C$8,Reglas!$C$9)) | M69: Mía | N69: 4 | O69: Bajo | P69: Gran herramienta para planificar y evitar eventos negativos.
A70: T069 | B70: Fortuna del temerario | C70: 4 | D70: =IF(Q70="Sí",0,C70*Reglas!$C$5) | E70: Civil | F70: Saber | G70: Opcional | H70: Terreno y eventos | I70: Eventos | J70: Los efectos positivos de eventos en zonas riesgosas son un 25% mejores. | K70: Reservas de emergencia (T066) | L70: =IF(C70=1,0,CHOOSE(C70-1,Reglas!$C$6,Reglas!$C$7,Reglas!$C$8,Reglas!$C$9)) | M70: Mía | N70: 3 | O70: Bajo | P70: Premia jugar en terrenos difíciles. Falta definir cuáles son riesgosos.
A71: T070 | B71: Resistencia climática | C71: 4 | D71: =IF(Q71="Sí",0,C71*Reglas!$C$5) | E71: Civil | F71: Saber | G71: Opcional | H71: Terreno y eventos | I71: Eventos | J71: Los eventos negativos afectan un 50% menos a tus zonas riesgosas. | K71: Reservas de emergencia (T066) | L71: =IF(C71=1,0,CHOOSE(C71-1,Reglas!$C$6,Reglas!$C$7,Reglas!$C$8,Reglas!$C$9)) | M71: Mía | N71: 3 | O71: Bajo | P71: Contrapeso al riesgo del terreno.
A72: T071 | B72: Gran biblioteca | C72: 5 | D72: =IF(Q72="Sí",0,C72*Reglas!$C$5) | E72: Construcción | F72: Saber | G72: Opcional | H72: Biblioteca | I72: Mejora de edificio | J72: La Biblioteca da +5 de tecnología por trabajador. | K72: Archivo (T067) | L72: =IF(C72=1,0,CHOOSE(C72-1,Reglas!$C$6,Reglas!$C$7,Reglas!$C$8,Reglas!$C$9)) | M72: Mía | N72: 3 | O72: Alto | P72: Con 4 trabajadores son +20 de tecnología por paso. Con ese ritmo, el árbol completo se acorta mucho.
A73: T072 | B73: Pronóstico | C73: 5 | D73: =IF(Q73="Sí",0,C73*Reglas!$C$5) | E73: Civil | F73: Saber | G73: Opcional | H73: Saber | I73: Eventos | J73: Una vez cada 10 rondas puedes evitar un evento negativo. | K73: Astronomía (T068) | L73: =IF(C73=1,0,CHOOSE(C73-1,Reglas!$C$6,Reglas!$C$7,Reglas!$C$8,Reglas!$C$9)) | M73: Mía | N73: 4 | O73: Bajo | P73: Poderosa, pero con límite de uso, lo que la hace justa.
A74: T073 | B74: Almacenes | C74: 1 | D74: =IF(Q74="Sí",0,C74*Reglas!$C$5) | E74: Construcción | F74: Logística | G74: Vertebral | H74: Almacén | I74: Desbloqueo de edificio | J74: Permite construir el Almacén: +10 de capacidad de almacenamiento (comida y producción) por nivel del edificio. | K74: — | L74: =IF(C74=1,0,CHOOSE(C74-1,Reglas!$C$6,Reglas!$C$7,Reglas!$C$8,Reglas!$C$9)) | M74: Tuya | N74: 5 | O74: Bajo | P74: Base de toda la logística. Barata, clara y útil desde el primer paso. | Q74: Sí
A75: T074 | B75: Caminos | C75: 1 | D75: =IF(Q75="Sí",0,C75*Reglas!$C$5) | E75: Construcción | F75: Logística | G75: Vertebral | H75: Camino | I75: Desbloqueo de edificio | J75: Permite construir el Camino: mover comida y producción desde o hacia la zona cuesta la mitad de oro (redondeando hacia arriba). | K75: — | L75: =IF(C75=1,0,CHOOSE(C75-1,Reglas!$C$6,Reglas!$C$7,Reglas!$C$8,Reglas!$C$9)) | M75: Tuya | N75: 5 | O75: Bajo | P75: Hace rentables las zonas lejanas. Imprescindible en mapas lentos como Fortaleza o Espiral. | Q75: Sí
A76: T075 | B76: Camino civil I | C76: 2 | D76: =IF(Q76="Sí",0,C76*Reglas!$C$5) | E76: Construcción | F76: Logística | G76: Vertebral | H76: Camino | I76: Especialización de edificio | J76: Esp.: los civiles pueden moverse en una dirección de forma inmediata y, al llegar, producir, descansar, etc. en ese mismo paso. | K76: Caminos (T074) | L76: =IF(C76=1,0,CHOOSE(C76-1,Reglas!$C$6,Reglas!$C$7,Reglas!$C$8,Reglas!$C$9)) | M76: Tuya | N76: 4 | O76: Medio | P76: Muy fuerte: elimina el costo de 'no producir el paso en que te mueves'. Choca con la regla actual, así que hay que definirlo bien.
A77: T076 | B77: Red de caminos I | C77: 3 | D77: =IF(Q77="Sí",0,C77*Reglas!$C$5) | E77: Construcción | F77: Logística | G77: Vertebral | H77: Camino | I77: Mejora de edificio | J77: Mover comida y producción que pase por esta zona cuesta 1/3 del total. | K77: Camino civil I (T075) | L77: =IF(C77=1,0,CHOOSE(C77-1,Reglas!$C$6,Reglas!$C$7,Reglas!$C$8,Reglas!$C$9)) | M77: Tuya | N77: 5 | O77: Medio | P77: Muy buena: hace casi gratuita la logística de una zona central y crea puntos estratégicos que todos querrán controlar.
A78: T077 | B78: Camino civil II | C78: 4 | D78: =IF(Q78="Sí",0,C78*Reglas!$C$5) | E78: Construcción | F78: Logística | G78: Vertebral | H78: Camino | I78: Especialización de edificio | J78: Esp.: al moverse, cada civil puede llevar hasta 5 unidades en total de comida o producción. | K78: Camino civil I (T075); Red de caminos I (T076) | L78: =IF(C78=1,0,CHOOSE(C78-1,Reglas!$C$6,Reglas!$C$7,Reglas!$C$8,Reglas!$C$9)) | M78: Tuya | N78: 4 | O78: Medio | P78: Abre una logística alternativa sin pagar oro. Aclarar si el movimiento civil sigue siendo gratis y si el recurso llega en el mismo paso.
A79: T078 | B79: Red de caminos II | C79: 5 | D79: =IF(Q79="Sí",0,C79*Reglas!$C$5) | E79: Construcción | F79: Logística | G79: Vertebral | H79: Camino | I79: Mejora de edificio | J79: Desbloquea La Calzada sin Fin, la maravilla de Logística (única en la partida): mover comida y producción por su zona es gratis mientras controles su zona. Solo se puede investigar si nadie la ha construido. | K79: Camino civil II (T077) | L79: =IF(C79=1,0,CHOOSE(C79-1,Reglas!$C$6,Reglas!$C$7,Reglas!$C$8,Reglas!$C$9)) | M79: Tuya | N79: 4 | O79: Alto | P79: Por sí sola no da su efecto: lo da la maravilla. Si otro la termina antes, pierdes la obra y recuperas la mitad de la producción, pero conservas la tecnología (cuenta para la victoria tecnológica).
A80: T079 | B80: Almacén de comida I | C80: 2 | D80: =IF(Q80="Sí",0,C80*Reglas!$C$5) | E80: Construcción | F80: Logística | G80: Opcional | H80: Almacén | I80: Especialización de edificio | J80: Esp.: el almacén guarda 10 más de comida. | K80: Almacenes (T073) | L80: =IF(C80=1,0,CHOOSE(C80-1,Reglas!$C$6,Reglas!$C$7,Reglas!$C$8,Reglas!$C$9)) | M80: Tuya | N80: 4 | O80: Bajo | P80: Buena para quien juega a crecer. Aclarar si un mismo almacén puede tener la especialización de comida y la de producción a la vez (se asume que no).
A81: T080 | B81: Almacén de producción I | C81: 2 | D81: =IF(Q81="Sí",0,C81*Reglas!$C$5) | E81: Construcción | F81: Logística | G81: Opcional | H81: Almacén | I81: Especialización de edificio | J81: Esp.: el almacén guarda 10 más de producción. | K81: Almacenes (T073) | L81: =IF(C81=1,0,CHOOSE(C81-1,Reglas!$C$6,Reglas!$C$7,Reglas!$C$8,Reglas!$C$9)) | M81: Tuya | N81: 4 | O81: Bajo | P81: Útil para juntar los 500 de la Maravilla sin depender tanto de la logística.
A82: T081 | B82: Almacenes económicos | C82: 2 | D82: =IF(Q82="Sí",0,C82*Reglas!$C$5) | E82: Construcción | F82: Logística | G82: Opcional | H82: Almacén | I82: Mejora de edificio | J82: El Almacén cuesta la mitad de producción. | K82: Almacenes (T073) | L82: =IF(C82=1,0,CHOOSE(C82-1,Reglas!$C$6,Reglas!$C$7,Reglas!$C$8,Reglas!$C$9)) | M82: Tuya | N82: 2 | O82: Bajo | P82: El Almacén ya es barato (20 de producción), así que ahorra solo 10. Casi nadie la elegirá; mejor ligarla a otro efecto.
A83: T082 | B83: Intereses del almacén I | C83: 2 | D83: =IF(Q83="Sí",0,C83*Reglas!$C$5) | E83: Construcción | F83: Logística | G83: Opcional | H83: Almacén | I83: Especialización de edificio | J83: Por cada 10 unidades de comida o producción almacenadas en la zona, el almacén genera 1 de oro. | K83: Almacenes (T073); Moneda (T032) | L83: =IF(C83=1,0,CHOOSE(C83-1,Reglas!$C$6,Reglas!$C$7,Reglas!$C$8,Reglas!$C$9)) | M83: Tuya | N83: 4 | O83: Medio | P83: Convierte reservas en oro y compite con gastarlas. Con el tope base de 10 por zona rinde apenas 1 de oro; mejora mucho con las ampliaciones.
A84: T083 | B84: Camino militar I | C84: 2 | D84: =IF(Q84="Sí",0,C84*Reglas!$C$5) | E84: Construcción | F84: Logística | G84: Opcional | H84: Camino | I84: Especialización de edificio | J84: Esp.: las unidades militares que se mueven desde esta zona obtienen 1 de iniciativa en los combates de esa ronda. | K84: Caminos (T074) | L84: =IF(C84=1,0,CHOOSE(C84-1,Reglas!$C$6,Reglas!$C$7,Reglas!$C$8,Reglas!$C$9)) | M84: Tuya | N84: 3 | O84: Bajo | P84: El '+1 de iniciativa' es ambiguo: como el número menor actúa primero, ¿es un +1 (más lento) o un −1 (más rápido)? Se propone −1, es decir, actúan antes.
A85: T084 | B85: Almacén de comida II | C85: 3 | D85: =IF(Q85="Sí",0,C85*Reglas!$C$5) | E85: Construcción | F85: Logística | G85: Opcional | H85: Almacén | I85: Especialización de edificio | J85: Esp.: el almacén guarda 20 más de comida (reemplaza el bono anterior). | K85: Almacén de comida I (T079) | L85: =IF(C85=1,0,CHOOSE(C85-1,Reglas!$C$6,Reglas!$C$7,Reglas!$C$8,Reglas!$C$9)) | M85: Tuya | N85: 4 | O85: Bajo | P85: Se asume que los bonos NO se acumulan (reemplazan al anterior). Si se acumularan, la reserva crecería mucho más rápido.
A86: T085 | B86: Almacén de producción II | C86: 3 | D86: =IF(Q86="Sí",0,C86*Reglas!$C$5) | E86: Construcción | F86: Logística | G86: Opcional | H86: Almacén | I86: Especialización de edificio | J86: Esp.: el almacén guarda 20 más de producción (reemplaza el bono anterior). | K86: Almacén de producción I (T080) | L86: =IF(C86=1,0,CHOOSE(C86-1,Reglas!$C$6,Reglas!$C$7,Reglas!$C$8,Reglas!$C$9)) | M86: Tuya | N86: 4 | O86: Bajo | P86: Misma duda que con la comida: se asume que no se acumula con el nivel anterior.
A87: T086 | B87: Almacén de comida III | C87: 4 | D87: =IF(Q87="Sí",0,C87*Reglas!$C$5) | E87: Construcción | F87: Logística | G87: Opcional | H87: Almacén | I87: Especialización de edificio | J87: Esp.: el almacén guarda 30 más de comida (reemplaza el bono anterior). | K87: Almacén de comida II (T084) | L87: =IF(C87=1,0,CHOOSE(C87-1,Reglas!$C$6,Reglas!$C$7,Reglas!$C$8,Reglas!$C$9)) | M87: Tuya | N87: 3 | O87: Medio | P87: Con un tope base de 10 por zona, +30 es cuadruplicar la reserva. Sirve para ahorrar para crecer, pero pierde valor si no hay presión de hambre.
... A105: T104 | B105: Dominio del terreno | C105: 5 | D105: =IF(Q105="Sí",0,C105*Reglas!$C$5) | E105: Civil | F105: Urbanismo | G105: Opcional | H105: Terreno y eventos | I105: Terreno | J105: Todos los bonos económicos de terreno se duplican. | K105: Terrazas (T027); Canteras de colina (T099) | L105: =IF(C105=1,0,CHOOSE(C105-1,Reglas!$C$6,Reglas!$C$7,Reglas!$C$8,Reglas!$C$9)) | M105: Mía | N105: 2 | O105: Alto | P105: Fuerte y simple, pero puede volver decisivas las zonas con buen terreno.
A106: T105 | B106: Hospitales | C106: 1 | D106: =IF(Q106="Sí",0,C106*Reglas!$C$5) | E106: Construcción | F106: Sanidad y población | G106: Vertebral | H106: Hospital | I106: Desbloqueo de edificio | J106: Permite construir el Hospital: los heridos de la zona se curan en la mitad de rondas (redondeando hacia arriba). | K106: — | L106: =IF(C106=1,0,CHOOSE(C106-1,Reglas!$C$6,Reglas!$C$7,Reglas!$C$8,Reglas!$C$9)) | M106: Tuya | N106: 5 | O106: Bajo | P106: Hace que las heridas duelan menos y vuelve atractivo pelear cerca de un hospital. | Q106: Sí
A107: T106 | B107: Parteras | C107: 1 | D107: =IF(Q107="Sí",0,C107*Reglas!$C$5) | E107: Civil | F107: Sanidad y población | G107: Vertebral | H107: Población | I107: Población | J107: El crecimiento de población cuesta 1 menos de comida (mínimo 1). | K107: — | L107: =IF(C107=1,0,CHOOSE(C107-1,Reglas!$C$6,Reglas!$C$7,Reglas!$C$8,Reglas!$C$9)) | M107: Mía | N107: 4 | O107: Bajo | P107: Pequeño ahorro desde el principio: ayuda a empezar a crecer.
A108: T107 | B108: Hospital civil I | C108: 2 | D108: =IF(Q108="Sí",0,C108*Reglas!$C$5) | E108: Construcción | F108: Sanidad y población | G108: Vertebral | H108: Hospital | I108: Especialización de edificio | J108: Esp.: los civiles, después de ser curados, tienen su eficiencia (cuánto producen o usan) duplicada durante dos rondas. | K108: Hospitales (T105) | L108: =IF(C108=1,0,CHOOSE(C108-1,Reglas!$C$6,Reglas!$C$7,Reglas!$C$8,Reglas!$C$9)) | M108: Tuya | N108: 4 | O108: Medio | P108: Buen incentivo para curar civiles. Puede ser muy fuerte si los curados son científicos o ingenieros.
A109: T108 | B109: Familias numerosas | C109: 2 | D109: =IF(Q109="Sí",0,C109*Reglas!$C$5) | E109: Civil | F109: Sanidad y población | G109: Vertebral | H109: Población | I109: Población | J109: El crecimiento de población cuesta 2 menos de comida (total, reemplaza al anterior). | K109: Parteras (T106) | L109: =IF(C109=1,0,CHOOSE(C109-1,Reglas!$C$6,Reglas!$C$7,Reglas!$C$8,Reglas!$C$9)) | M109: Mía | N109: 4 | O109: Bajo | P109: Premia seguir la rama. Hace falta ver cómo se combina con Edad de oro.
A110: T109 | B110: Hospital civil II | C110: 3 | D110: =IF(Q110="Sí",0,C110*Reglas!$C$5) | E110: Construcción | F110: Sanidad y población | G110: Vertebral | H110: Hospital | I110: Especialización de edificio | J110: Esp.: los civiles se curan en una ronda, sin importar el daño. | K110: Hospital civil I (T107) | L110: =IF(C110=1,0,CHOOSE(C110-1,Reglas!$C$6,Reglas!$C$7,Reglas!$C$8,Reglas!$C$9)) | M110: Tuya | N110: 4 | O110: Medio | P110: Casi anula el costo de las heridas civiles. Combina muy bien con el sistema de capturas.
A111: T110 | B111: Hospital civil III | C111: 4 | D111: =IF(Q111="Sí",0,C111*Reglas!$C$5) | E111: Construcción | F111: Sanidad y población | G111: Vertebral | H111: Hospital | I111: Especialización de edificio | J111: Esp.: todos los civiles de esta ciudad aumentan su eficiencia en 1. | K111: Hospital civil II (T109) | L111: =IF(C111=1,0,CHOOSE(C111-1,Reglas!$C$6,Reglas!$C$7,Reglas!$C$8,Reglas!$C$9)) | M111: Tuya | N111: 4 | O111: Medio | P111: Es más un edificio económico que un hospital. Buen cierre para la rama civil.
A112: T111 | B112: Hospital imperial | C112: 5 | D112: =IF(Q112="Sí",0,C112*Reglas!$C$5) | E112: Construcción | F112: Sanidad y población | G112: Vertebral | H112: Hospital | I112: Mejora de edificio | J112: Desbloquea Las Termas de la Salud, la maravilla de Sanidad y población (única en la partida): todas tus unidades tienen 2 de vida más mientras controles su zona. Solo se puede investigar si nadie la ha construido. | K112: Hospital civil III (T110) | L112: =IF(C112=1,0,CHOOSE(C112-1,Reglas!$C$6,Reglas!$C$7,Reglas!$C$8,Reglas!$C$9)) | M112: Tuya | N112: 2 | O112: Alto | P112: Por sí sola no da su efecto: lo da la maravilla. Si otro la termina antes, pierdes la obra y recuperas la mitad de la producción, pero conservas la tecnología (cuenta para la victoria tecnológica).
A113: T112 | B113: Hospital militar I | C113: 2 | D113: =IF(Q113="Sí",0,C113*Reglas!$C$5) | E113: Construcción | F113: Sanidad y población | G113: Opcional | H113: Hospital | I113: Especialización de edificio | J113: Esp.: los militares obtienen +1 de fuerza de combate durante dos rondas después de ser curados. | K113: Hospitales (T105) | L113: =IF(C113=1,0,CHOOSE(C113-1,Reglas!$C$6,Reglas!$C$7,Reglas!$C$8,Reglas!$C$9)) | M113: Tuya | N113: 4 | O113: Medio | P113: Interesante para mantener un hospital cerca del frente. Recordar que la fuerza máxima por defecto es 4.
A114: T113 | B114: Medicina popular | C114: 2 | D114: =IF(Q114="Sí",0,C114*Reglas!$C$5) | E114: Civil | F114: Sanidad y población | G114: Opcional | H114: Población | I114: Población | J114: Los civiles heridos se curan una ronda más rápido (mínimo 1). | K114: Parteras (T106) | L114: =IF(C114=1,0,CHOOSE(C114-1,Reglas!$C$6,Reglas!$C$7,Reglas!$C$8,Reglas!$C$9)) | M114: Mía | N114: 3 | O114: Medio | P114: Ahorra poco al inicio, pero es útil si hay muchos combates.
A115: T114 | B115: Colonos | C115: 2 | D115: =IF(Q115="Sí",0,C115*Reglas!$C$5) | E115: Civil | F115: Sanidad y población | G115: Opcional | H115: Población | I115: Población | J115: Las zonas vacías que ocupes reciben 2 civiles gratis. | K115: Parteras (T106) | L115: =IF(C115=1,0,CHOOSE(C115-1,Reglas!$C$6,Reglas!$C$7,Reglas!$C$8,Reglas!$C$9)) | M115: Mía | N115: 4 | O115: Bajo | P115: Impulsa la expansión, que era uno de los objetivos del diseño.
A116: T115 | B116: Hospital militar II | C116: 3 | D116: =IF(Q116="Sí",0,C116*Reglas!$C$5) | E116: Construcción | F116: Sanidad y población | G116: Opcional | H116: Hospital | I116: Especialización de edificio | J116: Esp.: los militares se curan en una ronda, sin importar el daño. | K116: Hospital militar I (T112) | L116: =IF(C116=1,0,CHOOSE(C116-1,Reglas!$C$6,Reglas!$C$7,Reglas!$C$8,Reglas!$C$9)) | M116: Tuya | N116: 4 | O116: Medio | P116: Muy fuerte en guerras largas: elimina el tiempo de recuperación. Hace que el hospital sea un objetivo clave.
A117: T116 | B117: Migraciones guiadas | C117: 3 | D117: =IF(Q117="Sí",0,C117*Reglas!$C$5) | E117: Civil | F117: Sanidad y población | G117: Opcional | H117: Población | I117: Población | J117: Los civiles que se mueven entre tus zonas adyacentes producen la mitad ese paso (en vez de nada). | K117: Familias numerosas (T108) | L117: =IF(C117=1,0,CHOOSE(C117-1,Reglas!$C$6,Reglas!$C$7,Reglas!$C$8,Reglas!$C$9)) | M117: Mía | N117: 3 | O117: Bajo | P117: Reduce una regla que pareció importante. Vigilar que no deje a los civiles demasiado móviles.
A118: T117 | B118: Pobladores resistentes | C118: 3 | D118: =IF(Q118="Sí",0,C118*Reglas!$C$5) | E118: Civil | F118: Sanidad y población | G118: Opcional | H118: Población | I118: Población | J118: Los civiles tienen +1 de vida. | K118: Medicina popular (T113) | L118: =IF(C118=1,0,CHOOSE(C118-1,Reglas!$C$6,Reglas!$C$7,Reglas!$C$8,Reglas!$C$9)) | M118: Mía | N118: 2 | O118: Alto | P118: Afecta mucho las capturas: con 4 de vida, capturar pueblos cuesta más.
... A158: T157 | B158: Trabucos | C158: 5 | D158: =IF(Q158="Sí",0,C158*Reglas!$C$5) | E158: Militar | F158: Armas y unidades | G158: Opcional | H158: Máquinas de asedio | I158: Unidad militar | J158: Los lanzapiedras pasan a nivel 3: +1 de ataque (2 de daño por unidad). | K158: Contrapesos (T151) | L158: =IF(C158=1,0,CHOOSE(C158-1,Reglas!$C$6,Reglas!$C$7,Reglas!$C$8,Reglas!$C$9)) | M158: Mía | N158: 3 | O158: Alto | P158: El daño de área llega a su máximo; es el elemento de mayor riesgo del combate.
A159: T158 | B159: Cuarteles | C159: 1 | D159: =IF(Q159="Sí",0,C159*Reglas!$C$5) | E159: Militar | F159: Cuartel y entrenamiento | G159: Vertebral | H159: Cuartel | I159: Desbloqueo de edificio | J159: Permite construir el Cuartel: los militares que trabajan ahí no consumen comida y, al movilizarse, pueden moverse una zona extra en un turno (el movimiento sigue costando oro). | K159: — | L159: =IF(C159=1,0,CHOOSE(C159-1,Reglas!$C$6,Reglas!$C$7,Reglas!$C$8,Reglas!$C$9)) | M159: Tuya | N159: 5 | O159: Bajo | P159: El motor de cualquier plan militar. Su ventaja económica es clara y el movimiento extra da ritmo. | Q159: Sí
A160: T159 | B160: Marcha forzada | C160: 2 | D160: =IF(Q160="Sí",0,C160*Reglas!$C$5) | E160: Militar | F160: Cuartel y entrenamiento | G160: Vertebral | H160: Cuartel | I160: Mejora de edificio | J160: El Cuartel permite moverse 2 zonas extra en un turno (en vez de 1). | K160: Cuarteles (T158) | L160: =IF(C160=1,0,CHOOSE(C160-1,Reglas!$C$6,Reglas!$C$7,Reglas!$C$8,Reglas!$C$9)) | M160: Mía | N160: 3 | O160: Medio | P160: En mapas con capitales a 3-7 pasos acelera mucho las guerras. Cada zona extra sigue costando oro.
A161: T160 | B161: Entrenamiento continuo | C161: 2 | D161: =IF(Q161="Sí",0,C161*Reglas!$C$5) | E161: Militar | F161: Cuartel y entrenamiento | G161: Vertebral | H161: Entrenamiento | I161: Combate | J161: Los militares ganan +2 de fuerza por ronda (en vez de +1) hasta el máximo. | K161: Cuarteles (T158) | L161: =IF(C161=1,0,CHOOSE(C161-1,Reglas!$C$6,Reglas!$C$7,Reglas!$C$8,Reglas!$C$9)) | M161: Mía | N161: 4 | O161: Bajo | P161: Premia mantener un ejército en pie.
A162: T161 | B162: Campo de entrenamiento | C162: 3 | D162: =IF(Q162="Sí",0,C162*Reglas!$C$5) | E162: Militar | F162: Cuartel y entrenamiento | G162: Vertebral | H162: Cuartel | I162: Especialización de edificio | J162: Esp.: los militares entrenados aquí empiezan con +1 de fuerza (hasta el máximo). | K162: Entrenamiento continuo (T160) | L162: =IF(C162=1,0,CHOOSE(C162-1,Reglas!$C$6,Reglas!$C$7,Reglas!$C$8,Reglas!$C$9)) | M162: Mía | N162: 4 | O162: Medio | P162: Da una ventaja real a quien invierte en un cuartel central.
A163: T162 | B163: Guardia de élite | C163: 4 | D163: =IF(Q163="Sí",0,C163*Reglas!$C$5) | E163: Militar | F163: Cuartel y entrenamiento | G163: Vertebral | H163: Cuartel | I163: Especialización de edificio | J163: Esp.: los militares que trabajan en este Cuartel tienen +1 de defensa. | K163: Campo de entrenamiento (T161) | L163: =IF(C163=1,0,CHOOSE(C163-1,Reglas!$C$6,Reglas!$C$7,Reglas!$C$8,Reglas!$C$9)) | M163: Mía | N163: 3 | O163: Medio | P163: Convierte a los trabajadores del cuartel en una guarnición fuerte en el lugar donde están.
A164: T163 | B164: Veteranos | C164: 5 | D164: =IF(Q164="Sí",0,C164*Reglas!$C$5) | E164: Militar | F164: Cuartel y entrenamiento | G164: Vertebral | H164: Entrenamiento | I164: Combate | J164: Desbloquea El Patio de Armas, la maravilla de Cuartel y entrenamiento (única en la partida): la fuerza máxima de las tropas sube de 4 a 5 mientras controles su zona. Solo se puede investigar si nadie la ha construido. | K164: Guardia de élite (T162) | L164: =IF(C164=1,0,CHOOSE(C164-1,Reglas!$C$6,Reglas!$C$7,Reglas!$C$8,Reglas!$C$9)) | M164: Mía | N164: 3 | O164: Medio | P164: Por sí sola no da su efecto: lo da la maravilla. Si otro la termina antes, pierdes la obra y recuperas la mitad de la producción, pero conservas la tecnología (cuenta para la victoria tecnológica).
A165: T164 | B165: Cuartel de instrucción | C165: 2 | D165: =IF(Q165="Sí",0,C165*Reglas!$C$5) | E165: Militar | F165: Cuartel y entrenamiento | G165: Opcional | H165: Cuartel | I165: Especialización de edificio | J165: Esp.: convertir un civil en soldado en este Cuartel cuesta 1 de producción menos. | K165: Cuarteles (T158) | L165: =IF(C165=1,0,CHOOSE(C165-1,Reglas!$C$6,Reglas!$C$7,Reglas!$C$8,Reglas!$C$9)) | M165: Mía | N165: 3 | O165: Bajo | P165: Ahorro modesto (de 2 a 1 de producción), pero útil para reclutar masivamente.
A166: T165 | B166: Lanceros | C166: 2 | D166: =IF(Q166="Sí",0,C166*Reglas!$C$5) | E166: Militar | F166: Cuartel y entrenamiento | G166: Opcional | H166: Entrenamiento | I166: Combate | J166: Los soldados básicos tienen +1 de ataque cuando defienden. | K166: Cuarteles (T158) | L166: =IF(C166=1,0,CHOOSE(C166-1,Reglas!$C$6,Reglas!$C$7,Reglas!$C$8,Reglas!$C$9)) | M166: Mía | N166: 3 | O166: Bajo | P166: Da un rol propio al soldado básico.
...

Sheet Ramas
B1: Las 12 ramas y su columna vertebral
B2: Costo hasta nivel 4 = lo necesario para poder investigar el nivel 5 de la rama. Costo de la columna = incluye la tecnología vertebral de nivel 5.
B4: Rama | C4: Tipo | D4: Tecnologías | E4: Vertebrales | F4: Opcionales | G4: Costo hasta nivel 4 (columna) | H4: Costo de la columna completa | I4: Valoración media | J4: Riesgo alto
B5: Agricultura | C5: Civil | D5: =COUNTIF(Tecnologías!$F$2:$F$204,B5) | E5: =COUNTIFS(Tecnologías!$F$2:$F$204,B5,Tecnologías!$G$2:$G$204,"Vertebral") | F5: =COUNTIFS(Tecnologías!$F$2:$F$204,B5,Tecnologías!$G$2:$G$204,"Opcional") | G5: =SUMIFS(Tecnologías!$D$2:$D$204,Tecnologías!$F$2:$F$204,B5,Tecnologías!$G$2:$G$204,"Vertebral",Tecnologías!$C$2:$C$204,"<=4") | H5: =SUMIFS(Tecnologías!$D$2:$D$204,Tecnologías!$F$2:$F$204,B5,Tecnologías!$G$2:$G$204,"Vertebral") | I5: =AVERAGEIF(Tecnologías!$F$2:$F$204,B5,Tecnologías!$N$2:$N$204) | J5: =COUNTIFS(Tecnologías!$F$2:$F$204,B5,Tecnologías!$O$2:$O$204,"Alto")
B6: Producción | C6: Civil | D6: =COUNTIF(Tecnologías!$F$2:$F$204,B6) | E6: =COUNTIFS(Tecnologías!$F$2:$F$204,B6,Tecnologías!$G$2:$G$204,"Vertebral") | F6: =COUNTIFS(Tecnologías!$F$2:$F$204,B6,Tecnologías!$G$2:$G$204,"Opcional") | G6: =SUMIFS(Tecnologías!$D$2:$D$204,Tecnologías!$F$2:$F$204,B6,Tecnologías!$G$2:$G$204,"Vertebral",Tecnologías!$C$2:$C$204,"<=4") | H6: =SUMIFS(Tecnologías!$D$2:$D$204,Tecnologías!$F$2:$F$204,B6,Tecnologías!$G$2:$G$204,"Vertebral") | I6: =AVERAGEIF(Tecnologías!$F$2:$F$204,B6,Tecnologías!$N$2:$N$204) | J6: =COUNTIFS(Tecnologías!$F$2:$F$204,B6,Tecnologías!$O$2:$O$204,"Alto")
B7: Comercio | C7: Civil | D7: =COUNTIF(Tecnologías!$F$2:$F$204,B7) | E7: =COUNTIFS(Tecnologías!$F$2:$F$204,B7,Tecnologías!$G$2:$G$204,"Vertebral") | F7: =COUNTIFS(Tecnologías!$F$2:$F$204,B7,Tecnologías!$G$2:$G$204,"Opcional") | G7: =SUMIFS(Tecnologías!$D$2:$D$204,Tecnologías!$F$2:$F$204,B7,Tecnologías!$G$2:$G$204,"Vertebral",Tecnologías!$C$2:$C$204,"<=4") | H7: =SUMIFS(Tecnologías!$D$2:$D$204,Tecnologías!$F$2:$F$204,B7,Tecnologías!$G$2:$G$204,"Vertebral") | I7: =AVERAGEIF(Tecnologías!$F$2:$F$204,B7,Tecnologías!$N$2:$N$204) | J7: =COUNTIFS(Tecnologías!$F$2:$F$204,B7,Tecnologías!$O$2:$O$204,"Alto")
B8: Saber | C8: Civil | D8: =COUNTIF(Tecnologías!$F$2:$F$204,B8) | E8: =COUNTIFS(Tecnologías!$F$2:$F$204,B8,Tecnologías!$G$2:$G$204,"Vertebral") | F8: =COUNTIFS(Tecnologías!$F$2:$F$204,B8,Tecnologías!$G$2:$G$204,"Opcional") | G8: =SUMIFS(Tecnologías!$D$2:$D$204,Tecnologías!$F$2:$F$204,B8,Tecnologías!$G$2:$G$204,"Vertebral",Tecnologías!$C$2:$C$204,"<=4") | H8: =SUMIFS(Tecnologías!$D$2:$D$204,Tecnologías!$F$2:$F$204,B8,Tecnologías!$G$2:$G$204,"Vertebral") | I8: =AVERAGEIF(Tecnologías!$F$2:$F$204,B8,Tecnologías!$N$2:$N$204) | J8: =COUNTIFS(Tecnologías!$F$2:$F$204,B8,Tecnologías!$O$2:$O$204,"Alto")
B9: Logística | C9: Construcción | D9: =COUNTIF(Tecnologías!$F$2:$F$204,B9) | E9: =COUNTIFS(Tecnologías!$F$2:$F$204,B9,Tecnologías!$G$2:$G$204,"Vertebral") | F9: =COUNTIFS(Tecnologías!$F$2:$F$204,B9,Tecnologías!$G$2:$G$204,"Opcional") | G9: =SUMIFS(Tecnologías!$D$2:$D$204,Tecnologías!$F$2:$F$204,B9,Tecnologías!$G$2:$G$204,"Vertebral",Tecnologías!$C$2:$C$204,"<=4") | H9: =SUMIFS(Tecnologías!$D$2:$D$204,Tecnologías!$F$2:$F$204,B9,Tecnologías!$G$2:$G$204,"Vertebral") | I9: =AVERAGEIF(Tecnologías!$F$2:$F$204,B9,Tecnologías!$N$2:$N$204) | J9: =COUNTIFS(Tecnologías!$F$2:$F$204,B9,Tecnologías!$O$2:$O$204,"Alto")
B10: Urbanismo | C10: Construcción | D10: =COUNTIF(Tecnologías!$F$2:$F$204,B10) | E10: =COUNTIFS(Tecnologías!$F$2:$F$204,B10,Tecnologías!$G$2:$G$204,"Vertebral") | F10: =COUNTIFS(Tecnologías!$F$2:$F$204,B10,Tecnologías!$G$2:$G$204,"Opcional") | G10: =SUMIFS(Tecnologías!$D$2:$D$204,Tecnologías!$F$2:$F$204,B10,Tecnologías!$G$2:$G$204,"Vertebral",Tecnologías!$C$2:$C$204,"<=4") | H10: =SUMIFS(Tecnologías!$D$2:$D$204,Tecnologías!$F$2:$F$204,B10,Tecnologías!$G$2:$G$204,"Vertebral") | I10: =AVERAGEIF(Tecnologías!$F$2:$F$204,B10,Tecnologías!$N$2:$N$204) | J10: =COUNTIFS(Tecnologías!$F$2:$F$204,B10,Tecnologías!$O$2:$O$204,"Alto")
B11: Sanidad y población | C11: Construcción | D11: =COUNTIF(Tecnologías!$F$2:$F$204,B11) | E11: =COUNTIFS(Tecnologías!$F$2:$F$204,B11,Tecnologías!$G$2:$G$204,"Vertebral") | F11: =COUNTIFS(Tecnologías!$F$2:$F$204,B11,Tecnologías!$G$2:$G$204,"Opcional") | G11: =SUMIFS(Tecnologías!$D$2:$D$204,Tecnologías!$F$2:$F$204,B11,Tecnologías!$G$2:$G$204,"Vertebral",Tecnologías!$C$2:$C$204,"<=4") | H11: =SUMIFS(Tecnologías!$D$2:$D$204,Tecnologías!$F$2:$F$204,B11,Tecnologías!$G$2:$G$204,"Vertebral") | I11: =AVERAGEIF(Tecnologías!$F$2:$F$204,B11,Tecnologías!$N$2:$N$204) | J11: =COUNTIFS(Tecnologías!$F$2:$F$204,B11,Tecnologías!$O$2:$O$204,"Alto")
B12: Diplomacia e imperio | C12: Civil | D12: =COUNTIF(Tecnologías!$F$2:$F$204,B12) | E12: =COUNTIFS(Tecnologías!$F$2:$F$204,B12,Tecnologías!$G$2:$G$204,"Vertebral") | F12: =COUNTIFS(Tecnologías!$F$2:$F$204,B12,Tecnologías!$G$2:$G$204,"Opcional") | G12: =SUMIFS(Tecnologías!$D$2:$D$204,Tecnologías!$F$2:$F$204,B12,Tecnologías!$G$2:$G$204,"Vertebral",Tecnologías!$C$2:$C$204,"<=4") | H12: =SUMIFS(Tecnologías!$D$2:$D$204,Tecnologías!$F$2:$F$204,B12,Tecnologías!$G$2:$G$204,"Vertebral") | I12: =AVERAGEIF(Tecnologías!$F$2:$F$204,B12,Tecnologías!$N$2:$N$204) | J12: =COUNTIFS(Tecnologías!$F$2:$F$204,B12,Tecnologías!$O$2:$O$204,"Alto")
B13: Armas y unidades | C13: Militar | D13: =COUNTIF(Tecnologías!$F$2:$F$204,B13) | E13: =COUNTIFS(Tecnologías!$F$2:$F$204,B13,Tecnologías!$G$2:$G$204,"Vertebral") | F13: =COUNTIFS(Tecnologías!$F$2:$F$204,B13,Tecnologías!$G$2:$G$204,"Opcional") | G13: =SUMIFS(Tecnologías!$D$2:$D$204,Tecnologías!$F$2:$F$204,B13,Tecnologías!$G$2:$G$204,"Vertebral",Tecnologías!$C$2:$C$204,"<=4") | H13: =SUMIFS(Tecnologías!$D$2:$D$204,Tecnologías!$F$2:$F$204,B13,Tecnologías!$G$2:$G$204,"Vertebral") | I13: =AVERAGEIF(Tecnologías!$F$2:$F$204,B13,Tecnologías!$N$2:$N$204) | J13: =COUNTIFS(Tecnologías!$F$2:$F$204,B13,Tecnologías!$O$2:$O$204,"Alto")
B14: Cuartel y entrenamiento | C14: Militar | D14: =COUNTIF(Tecnologías!$F$2:$F$204,B14) | E14: =COUNTIFS(Tecnologías!$F$2:$F$204,B14,Tecnologías!$G$2:$G$204,"Vertebral") | F14: =COUNTIFS(Tecnologías!$F$2:$F$204,B14,Tecnologías!$G$2:$G$204,"Opcional") | G14: =SUMIFS(Tecnologías!$D$2:$D$204,Tecnologías!$F$2:$F$204,B14,Tecnologías!$G$2:$G$204,"Vertebral",Tecnologías!$C$2:$C$204,"<=4") | H14: =SUMIFS(Tecnologías!$D$2:$D$204,Tecnologías!$F$2:$F$204,B14,Tecnologías!$G$2:$G$204,"Vertebral") | I14: =AVERAGEIF(Tecnologías!$F$2:$F$204,B14,Tecnologías!$N$2:$N$204) | J14: =COUNTIFS(Tecnologías!$F$2:$F$204,B14,Tecnologías!$O$2:$O$204,"Alto")
B15: Defensa | C15: Militar | D15: =COUNTIF(Tecnologías!$F$2:$F$204,B15) | E15: =COUNTIFS(Tecnologías!$F$2:$F$204,B15,Tecnologías!$G$2:$G$204,"Vertebral") | F15: =COUNTIFS(Tecnologías!$F$2:$F$204,B15,Tecnologías!$G$2:$G$204,"Opcional") | G15: =SUMIFS(Tecnologías!$D$2:$D$204,Tecnologías!$F$2:$F$204,B15,Tecnologías!$G$2:$G$204,"Vertebral",Tecnologías!$C$2:$C$204,"<=4") | H15: =SUMIFS(Tecnologías!$D$2:$D$204,Tecnologías!$F$2:$F$204,B15,Tecnologías!$G$2:$G$204,"Vertebral") | I15: =AVERAGEIF(Tecnologías!$F$2:$F$204,B15,Tecnologías!$N$2:$N$204) | J15: =COUNTIFS(Tecnologías!$F$2:$F$204,B15,Tecnologías!$O$2:$O$204,"Alto")
B16: Guerra y conquista | C16: Militar | D16: =COUNTIF(Tecnologías!$F$2:$F$204,B16) | E16: =COUNTIFS(Tecnologías!$F$2:$F$204,B16,Tecnologías!$G$2:$G$204,"Vertebral") | F16: =COUNTIFS(Tecnologías!$F$2:$F$204,B16,Tecnologías!$G$2:$G$204,"Opcional") | G16: =SUMIFS(Tecnologías!$D$2:$D$204,Tecnologías!$F$2:$F$204,B16,Tecnologías!$G$2:$G$204,"Vertebral",Tecnologías!$C$2:$C$204,"<=4") | H16: =SUMIFS(Tecnologías!$D$2:$D$204,Tecnologías!$F$2:$F$204,B16,Tecnologías!$G$2:$G$204,"Vertebral") | I16: =AVERAGEIF(Tecnologías!$F$2:$F$204,B16,Tecnologías!$N$2:$N$204) | J16: =COUNTIFS(Tecnologías!$F$2:$F$204,B16,Tecnologías!$O$2:$O$204,"Alto")
B17: Total | D17: =SUM(D5:D16) | E17: =SUM(E5:E16) | F17: =SUM(F5:F16) | G17: =SUM(G5:G16) | H17: =SUM(H5:H16) | J17: =SUM(J5:J16)

Sheet Resumen
B1: Resumen del árbol
B3: Tecnologías por nivel y tipo
B4: Nivel | C4: Civil | D4: Construcción | E4: Militar | F4: Total | G4: Costo c/u | H4: Costo total
B5: 1 | C5: =COUNTIFS(Tecnologías!$C$2:$C$204,$B5,Tecnologías!$E$2:$E$204,"Civil") | D5: =COUNTIFS(Tecnologías!$C$2:$C$204,$B5,Tecnologías!$E$2:$E$204,"Construcción") | E5: =COUNTIFS(Tecnologías!$C$2:$C$204,$B5,Tecnologías!$E$2:$E$204,"Militar") | F5: =SUM(C5:E5) | G5: =B5*Reglas!$C$5 | H5: =F5*G5
B6: 2 | C6: =COUNTIFS(Tecnologías!$C$2:$C$204,$B6,Tecnologías!$E$2:$E$204,"Civil") | D6: =COUNTIFS(Tecnologías!$C$2:$C$204,$B6,Tecnologías!$E$2:$E$204,"Construcción") | E6: =COUNTIFS(Tecnologías!$C$2:$C$204,$B6,Tecnologías!$E$2:$E$204,"Militar") | F6: =SUM(C6:E6) | G6: =B6*Reglas!$C$5 | H6: =F6*G6
B7: 3 | C7: =COUNTIFS(Tecnologías!$C$2:$C$204,$B7,Tecnologías!$E$2:$E$204,"Civil") | D7: =COUNTIFS(Tecnologías!$C$2:$C$204,$B7,Tecnologías!$E$2:$E$204,"Construcción") | E7: =COUNTIFS(Tecnologías!$C$2:$C$204,$B7,Tecnologías!$E$2:$E$204,"Militar") | F7: =SUM(C7:E7) | G7: =B7*Reglas!$C$5 | H7: =F7*G7
B8: 4 | C8: =COUNTIFS(Tecnologías!$C$2:$C$204,$B8,Tecnologías!$E$2:$E$204,"Civil") | D8: =COUNTIFS(Tecnologías!$C$2:$C$204,$B8,Tecnologías!$E$2:$E$204,"Construcción") | E8: =COUNTIFS(Tecnologías!$C$2:$C$204,$B8,Tecnologías!$E$2:$E$204,"Militar") | F8: =SUM(C8:E8) | G8: =B8*Reglas!$C$5 | H8: =F8*G8
B9: 5 | C9: =COUNTIFS(Tecnologías!$C$2:$C$204,$B9,Tecnologías!$E$2:$E$204,"Civil") | D9: =COUNTIFS(Tecnologías!$C$2:$C$204,$B9,Tecnologías!$E$2:$E$204,"Construcción") | E9: =COUNTIFS(Tecnologías!$C$2:$C$204,$B9,Tecnologías!$E$2:$E$204,"Militar") | F9: =SUM(C9:E9) | G9: =B9*Reglas!$C$5 | H9: =F9*G9
B10: Total | C10: =SUM(C5:C9) | D10: =SUM(D5:D9) | E10: =SUM(E5:E9) | F10: =SUM(F5:F9) | H10: =SUM(H5:H9)
B12: Origen y valoración
B13: Origen | C13: Cantidad | D13: Valoración media
B14: Tuya | C14: =COUNTIF(Tecnologías!$M$2:$M$204,B14) | D14: =AVERAGEIF(Tecnologías!$M$2:$M$204,B14,Tecnologías!$N$2:$N$204)
B15: Mía | C15: =COUNTIF(Tecnologías!$M$2:$M$204,B15) | D15: =AVERAGEIF(Tecnologías!$M$2:$M$204,B15,Tecnologías!$N$2:$N$204)
B16: Todas | C16: =SUM(C14:C15) | D16: =AVERAGE(Tecnologías!$N$2:$N$204)
B18: Riesgo de balance
B19: Riesgo | C19: Cantidad
B20: Alto | C20: =COUNTIF(Tecnologías!$O$2:$O$204,B20)
B21: Medio | C21: =COUNTIF(Tecnologías!$O$2:$O$204,B21)
B22: Bajo | C22: =COUNTIF(Tecnologías!$O$2:$O$204,B22)
B24: Columna vertebral y opcionales
B25: Columna | C25: Cantidad | D25: Costo total
B26: Vertebral | C26: =COUNTIF(Tecnologías!$G$2:$G$204,B26) | D26: =SUMIF(Tecnologías!$G$2:$G$204,B26,Tecnologías!$D$2:$D$204)
B27: Opcional | C27: =COUNTIF(Tecnologías!$G$2:$G$204,B27) | D27: =SUMIF(Tecnologías!$G$2:$G$204,B27,Tecnologías!$D$2:$D$204)
